{
  "settings": {
    "aisles": 1,
    "blocks": 1,
    "cellsPerBlock": 2
  },
  "drones": [
    {
      "id": "Normal speed",
      "startPosition": {
        "x": 0,
        "y": 0
      },
      "speed": 1,
      "operations": [
        "SOUTH",
        "SOUTH"
      ]
    }
  ],
  "cells": [
    {
      "row": 0,
      "col": 0,
      "isActive": true,
      "timeAtLastScan": -50000
    },
    {
      "row": 0,
      "col": 1,
      "isActive": true,
      "timeAtLastScan": -50000
    },
    {
      "row": 1,
      "col": 0,
      "isActive": true,
      "timeAtLastScan": -50000
    },
    {
      "row": 1,
      "col": 1,
      "isActive": true,
      "timeAtLastScan": -50000
    }
  ]
}
